python_imagesearch/__init__.py
python_imagesearch/imagesearch.py
python_imagesearch-1.3.0.dist-info/LICENSE
python_imagesearch-1.3.0.dist-info/METADATA
python_imagesearch-1.3.0.dist-info/WHEEL
python_imagesearch-1.3.0.dist-info/top_level.txt
python_imagesearch-1.3.0.dist-info/RECORD
