Metadata-Version: 2.1
Name: python-imagesearch
Version: 1.3.0
Summary: A wrapper around openCv to perform image searching
Home-page: https://github.com/drov0/python-imagesearch
Author: Martin Lees
Author-email: drov.fr@protonmail.com
License: UNKNOWN
Platform: UNKNOWN
Classifier: Programming Language :: Python :: 3
Classifier: License :: OSI Approved :: MIT License
Classifier: Operating System :: OS Independent
Requires-Python: >=3.5
License-File: LICENSE
